DataSystem/main.py
DataSystem-1.0.0.dist-info/METADATA
DataSystem-1.0.0.dist-info/WHEEL
DataSystem-1.0.0.dist-info/top_level.txt
DataSystem-1.0.0.dist-info/RECORD
