Metadata-Version: 2.1
Name: DataSystem
Version: 1.0.0
Summary: A package to retrieve system information
Home-page: UNKNOWN
Author: Sepehr0Day
License: UNKNOWN
Platform: UNKNOWN
Classifier: Development Status :: 5 - Production/Stable
Classifier: Intended Audience :: Developers
Classifier: License :: OSI Approved :: MIT License
Classifier: Programming Language :: Python :: 3
Classifier: Programming Language :: Python :: 3.7
Classifier: Programming Language :: Python :: 3.8
Classifier: Programming Language :: Python :: 3.9
Requires-Dist: GPUtil
Requires-Dist: psutil
Requires-Dist: py-cpuinfo
Requires-Dist: python-dateutil
